edc_lab_results/__init__.py
edc_lab_results/action_items.py
edc_lab_results/apps.py
edc_lab_results/calculate_missing.py
edc_lab_results/constants.py
edc_lab_results/fieldsets.py
edc_lab_results/get_summary.py
edc_lab_results/models.py
edc_lab_results/admin/__init__.py
edc_lab_results/admin/blood_results_modeladmin_mixin.py
edc_lab_results/admin/reportable_results_modeladmin_mixin.py
edc_lab_results/form_validator_mixins/__init__.py
edc_lab_results/form_validator_mixins/blood_results_fbg_form_validator_mixin.py
edc_lab_results/form_validator_mixins/blood_results_form_validator_mixin.py
edc_lab_results/form_validator_mixins/blood_results_glu_form_validator_mixin.py
edc_lab_results/model_mixins/__init__.py
edc_lab_results/model_mixins/blood_result_model_mixin.py
edc_lab_results/model_mixins/electrolytes_model_mixins.py
edc_lab_results/model_mixins/fbc_model_mixins.py
edc_lab_results/model_mixins/fbg_model_mixin.py
edc_lab_results/model_mixins/glucose_model_mixin.py
edc_lab_results/model_mixins/hba1c_model_mixin.py
edc_lab_results/model_mixins/insulin_model_mixin.py
edc_lab_results/model_mixins/lft_model_mixins.py
edc_lab_results/model_mixins/lipid_model_mixins.py
edc_lab_results/model_mixins/proteinuria_model_mixin.py
edc_lab_results/model_mixins/rft_model_mixins.py
edc_lab_results/tests/__init__.py
edc_lab_results/tests/consents.py
edc_lab_results/tests/forms.py
edc_lab_results/tests/holidays.csv
edc_lab_results/tests/lab_profiles.py
edc_lab_results/tests/models.py
edc_lab_results/tests/test_case_mixin.py
edc_lab_results/tests/test_settings.py
edc_lab_results/tests/urls.py
edc_lab_results/tests/visit_schedule.py
edc_lab_results/tests/etc/user-aes-local.key
edc_lab_results/tests/etc/user-aes-restricted.key
edc_lab_results/tests/etc/user-rsa-local-private.pem
edc_lab_results/tests/etc/user-rsa-local-public.pem
edc_lab_results/tests/etc/user-rsa-restricted-private.pem
edc_lab_results/tests/etc/user-rsa-restricted-public.pem
edc_lab_results/tests/etc/user-salt-local.key
edc_lab_results-1.0.2.dist-info/licenses/AUTHORS.rst
edc_lab_results-1.0.2.dist-info/licenses/LICENSE
edc_lab_results-1.0.2.dist-info/METADATA
edc_lab_results-1.0.2.dist-info/WHEEL
edc_lab_results-1.0.2.dist-info/top_level.txt
edc_lab_results-1.0.2.dist-info/RECORD
